setup.py
c_sql/__init__.py
c_sql.egg-info/PKG-INFO
c_sql.egg-info/SOURCES.txt
c_sql.egg-info/dependency_links.txt
c_sql.egg-info/top_level.txt