Metadata-Version: 2.1
Name: c-sql
Version: 0.0.1
Summary: sql query package
Home-page: https://www.cnblogs.com/Evan-fanfan/
Author: evanyang
Author-email: lightyiyi@qq.com
License: MIT tencent_message
Platform: UNKNOWN
